[null,{"name":"update","permissions":"MANAGE_EMOJIS","restriction":"1","actions":[{"channel":"0","varName":"","message":"**Your using the latest version of the gen !**\n\n**No need to update**","storage":"0","varName2":"","name":"Send Message"}]},{"name":"version","permissions":"MANAGE_EMOJIS","restriction":"1","actions":[{"channel":"0","varName":"","message":"**NitroGen version : 1.0.0.b**","storage":"0","varName2":"","name":"Send Message"}]},{"name":"status","permissions":"NONE","restriction":"2","actions":[{"gameName":"Pornhub","gameLink":"","name":"Set Bot Game"},{"status":"3","name":"Set Bot Status"}]},{"name":"help","permissions":"NONE","restriction":"1","actions":[{"title":"NitroGen commands","author":"","color":"#ffa6c9","timestamp":"false","url":"","authorIcon":"","imageUrl":"","thumbUrl":"","storage":"1","varName":"","name":"Create Embed Message"},{"storage":"1","varName":"","message":"**==============================================\n$version   -- checks version of the premium gen\n$update    -- checks if any update released\n$updatelogs -- see what updates have been added\n===============================================**","name":"Set Embed Description"},{"storage":"1","varName":"","channel":"0","varName2":"","name":"Send Embed Message"}]},{"name":"updatelogs","permissions":"NONE","restriction":"1","actions":[{"title":"NitroGen Logs","author":"","color":"#ffa6c9","timestamp":"false","url":"","authorIcon":"","imageUrl":"","thumbUrl":"","storage":"1","varName":"","name":"Create Embed Message"},{"storage":"1","varName":"","message":"**===========================================================\nadding randomizer\nAdding logs\nAdding devlogs\nAdding genlogs\nAdding design changes\nAdding more speed\nAdding more stablity\n///////UPDATE 1 RELEASED :white_check_mark:\\\\\\\\\n===========================================================\nAdding good hits file save\nAdding bad hits file save\n/////Update 2 NOT RELEASED:no_entry:\\\\\\\nProgress : 50%\n===========================================================**","name":"Set Embed Description"},{"storage":"1","varName":"","channel":"0","varName2":"","name":"Send Embed Message"}]}]